SNOSHEWS.cpython-311-darwin.so
mstl/algorithm2 function templates.cpp
mstl/algorithm2.h
mstl/bitset2.h
mstl/errors2 member templates.cpp
mstl/errors2.cpp
mstl/errors2.h
mstl/expression member templates.cpp
mstl/expression.h
mstl/functional2.h
mstl/messages.cpp
mstl/messages.h
mstl/miscellaneous functions templates.cpp
mstl/miscellaneous functions.cpp
mstl/miscellaneous functions.h
mstl/mstl.h
mstl/sort function templates.cpp
mstl/sort.h
mstl/stdarg2.cpp
mstl/stdarg2.h
mstl/template array function templates.cpp
mstl/template array member templates.cpp
mstl/template array.h
mstl/math2/math2 function templates.cpp
mstl/math2/math2.h
mstl/math2/number.h
mstl/math2/algebra/column and row vectors member templates.cpp
mstl/math2/algebra/column and row vectors.cpp
mstl/math2/algebra/column and row vectors.h
mstl/math2/algebra/linear algebra errors.h
mstl/math2/algebra/linear algebra function templates.cpp
mstl/math2/algebra/linear algebra.cpp
mstl/math2/algebra/linear algebra.h
mstl/math2/algebra/mmatrix member templates.cpp
mstl/math2/algebra/mmatrix.cpp
mstl/math2/algebra/mmatrix.h
mstl/math2/algebra/mvector errors.h
mstl/math2/algebra/mvector function templates.cpp
mstl/math2/algebra/mvector member templates.cpp
mstl/math2/algebra/mvector.h
mstl/math2/analysis/algorithm3.cpp
mstl/math2/analysis/algorithm3.h
mstl/math2/analysis/complex2 templates.cpp
mstl/math2/analysis/complex2.cpp
mstl/math2/analysis/complex2.h
mstl/math2/analysis/derivative.cpp
mstl/math2/analysis/derivative.h
mstl/math2/analysis/interpolation templates.cpp
mstl/math2/analysis/interpolation.h
mstl/math2/analysis/ode templates.cpp
mstl/math2/analysis/ode.h
mstl/math2/analysis/polynomial templates.cpp
mstl/math2/analysis/polynomial.cpp
mstl/math2/analysis/polynomial.h
mstl/math2/analysis/roots templates.cpp
mstl/math2/analysis/roots.cpp
mstl/math2/analysis/roots.h
mstl/math2/analysis/runge kutta templates.cpp
mstl/math2/analysis/runge kutta.cpp
mstl/math2/analysis/runge kutta.h
SNOSHEWS-1.0a1.dist-info/LICENSE
SNOSHEWS-1.0a1.dist-info/METADATA
SNOSHEWS-1.0a1.dist-info/WHEEL
SNOSHEWS-1.0a1.dist-info/top_level.txt
SNOSHEWS-1.0a1.dist-info/RECORD
